Metadata-Version: 2.1
Name: data-idr-access
Version: 0.0.1a2
Summary: easily use database
Home-page: 
Author: byscut
License: MIT
Requires-Python: >=3.7
